labelme2datasets/__init__.py
labelme2datasets/labelme_bbox_json2voc.py
labelme2datasets/labelme_json2dataset.py
labelme2datasets/split_voc_datasets.py
labelme2datasets/utils.py
labelme2datasets/version.py
labelme2datasets/voc2coco.py
labelme2datasets-0.0.3.dist-info/LICENSE
labelme2datasets-0.0.3.dist-info/METADATA
labelme2datasets-0.0.3.dist-info/WHEEL
labelme2datasets-0.0.3.dist-info/entry_points.txt
labelme2datasets-0.0.3.dist-info/top_level.txt
labelme2datasets-0.0.3.dist-info/RECORD
