Metadata-Version: 2.1
Name: labelme2datasets
Version: 0.0.3
Summary: python scripts to convert labelme-generated-jsons to voc/coco style datasets.
Home-page: https://github.com/veraposeidon/labelme2Datasets
Author: veraposeidon
Classifier: Programming Language :: Python :: 3.9
Classifier: License :: OSI Approved :: MIT License
Classifier: Operating System :: OS Independent
License-File: LICENSE
Requires-Dist: beautifulsoup4 ~=4.12.3
Requires-Dist: imgviz ~=1.7.5
Requires-Dist: labelme ~=5.4.1
Requires-Dist: progressbar ~=2.5
Requires-Dist: scikit-learn ~=1.4.2
Requires-Dist: xmltodict ~=0.13.0
Requires-Dist: setuptools ~=69.5.1
Requires-Dist: pillow ~=10.3.0
Requires-Dist: lxml ~=5.2.1
